scrapy_fingerprint/fingerprint_download_handler.py
scrapy_fingerprint-1.0.dist-info/METADATA
scrapy_fingerprint-1.0.dist-info/WHEEL
scrapy_fingerprint-1.0.dist-info/top_level.txt
scrapy_fingerprint-1.0.dist-info/RECORD
