Metadata-Version: 2.1
Name: scrapy_fingerprint
Version: 1.0
Summary: Request for scrapy to initiate browser fingerprinting
Home-page: https://github.com/tieyongjie/scrapy-fingerprint
Author: White.tie
Author-email: 1042798703@qq.com
License: UNKNOWN
Platform: UNKNOWN
Classifier: Environment :: Web Environment
Classifier: Intended Audience :: Developers
Classifier: Operating System :: OS Independent
Classifier: Topic :: Text Processing :: Indexing
Classifier: Topic :: Utilities
Classifier: Topic :: Internet
Classifier: Topic :: Software Development :: Libraries :: Python Modules
Classifier: Programming Language :: Python
Classifier: Programming Language :: Python :: 3.7
Classifier: Programming Language :: Python :: 3.8
Classifier: Programming Language :: Python :: 3.9
